setup_server.py
async_chat_server_kd.egg-info/PKG-INFO
async_chat_server_kd.egg-info/SOURCES.txt
async_chat_server_kd.egg-info/dependency_links.txt
async_chat_server_kd.egg-info/requires.txt
async_chat_server_kd.egg-info/top_level.txt
server/__init__.py
server/add_user.py
server/config_window.py
server/core.py
server/database.py
server/main_window.py
server/remove_user.py
server/stat_window.py