Metadata-Version: 1.0
Name: async-chat-server-kd
Version: 0.1
Summary: chat_server
Home-page: UNKNOWN
Author: Dmitry K
Author-email: k-d@bk.ru
License: UNKNOWN
Platform: UNKNOWN
